munge/__init__.py
munge/base.py
munge/cli.py
munge/click.py
munge/config.py
munge/util.py
munge/codec/__init__.py
munge/codec/all.py
munge/codec/json.py
munge/codec/mysql.py
munge/codec/toml.py
munge/codec/toml_toml.py
munge/codec/toml_tomlkit.py
munge/codec/yaml.py
munge-1.4.0.dist-info/METADATA
munge-1.4.0.dist-info/WHEEL
munge-1.4.0.dist-info/entry_points.txt
munge-1.4.0.dist-info/licenses/LICENSE.txt
munge-1.4.0.dist-info/RECORD
