Metadata-Version: 2.4
Name: munge
Version: 1.4.0
Summary: data manipulation library and client
Project-URL: Repository, https://github.com/20c/munge/
Author-email: 20C <code@20c.com>
License: Apache-2.0
License-File: LICENSE.txt
Classifier: License :: OSI Approved :: Apache Software License
Classifier: Programming Language :: Python :: 3.8
Classifier: Programming Language :: Python :: 3.9
Classifier: Programming Language :: Python :: 3.10
Classifier: Programming Language :: Python :: 3.11
Classifier: Programming Language :: Python :: 3.12
Classifier: Topic :: Software Development
Requires-Python: >=3.8
Requires-Dist: charset-normalizer>=3.3.0
Requires-Dist: click>=8.0.1
Requires-Dist: pyyaml>=6.0.1
Requires-Dist: requests>=2.32.0
Requires-Dist: toml>=0.10.2
Requires-Dist: tomlkit>=0.11.6
Requires-Dist: urllib3>=2.0.0
Provides-Extra: toml
Requires-Dist: toml>=0.10.2; extra == 'toml'
Provides-Extra: tomlkit
Requires-Dist: tomlkit>=0.7.2; extra == 'tomlkit'
Provides-Extra: yaml
Requires-Dist: pyyaml>=6.0.1; extra == 'yaml'
